[
    {
        "id": "about-page-greeting-title",
        "am": "የአካል ብቃት እንቅስቃሴዎን ከፍ ያድርጉ። ወጥነት ያለው ሁን። ውጤቶችን አግኝ።"
    },
    {
        "id": "about-page-greeting-description",
        "am": "TenaPrime ለእርስዎ ምርጡን የአካል ብቃት እንቅስቃሴ እቅድ ለማውጣት የAI ሃይልን እና የሰው ሳይንቲስቶችን እውቀት ይጠቀማል።"
    },
    {
        "id": "about-page-greeting-description-2",
        "am": "የተሻለ ረጅም ዕድሜ ለመኖር 5 ነገሮችን ማድረግ አለብዎት፡ ንቁ ይሁኑ፣ በትክክል ይመገቡ፣ በደንብ ይተኙ፣ በአዎንታዊነት ያስቡ እና ትርጉም ያላቸው ግንኙነቶችን ይፍጠሩ። እነዚህን ነገሮች ቀን በቀን ማድረግ ከጓደኞች ጋር የበለጠ ጊዜ፣ ከልጆች (እና ከልጅ ልጆች) ጋር የበለጠ ጊዜ እና ለመሳቅና ለመዋደድ የበለጠ ጊዜ ማለት ነው። ነገር ግን እነዚህን ነገሮች በትክክል ማድረግ ለብዙዎቻችን በጣም ከባድ ሊሆን ይችላል።"
    },
    {
        "id": "about-page-greeting-description-3",
        "am": "TenaPrime የሚገባው እዚህ ላይ ነው። ጥሩ ልማዶችን መገንባት አዝናኝ እና ሽልማት የሚያስገኝ በማድረግ እና ከNoom የጤና አሰልጣኞች እና ሌሎች ባለሙያዎች እና መሪ ድምፆች ጋር በቀጥታ ክፍለ ጊዜዎች በሚደጋገፍ ማህበረሰብ አካል በመሆን፣ የተሻለ ህይወት እንዲኖሩ ለመርዳት እዚህ አለን። ተልዕኳችን በሚቀጥሉት አስር ዓመታት ውስጥ ለእርስዎ መሰል ሰዎች 100 ሚሊዮን ተጨማሪ ጤናማ ዓመታትን ማስገኘት ነው። ሁሉም የሚጀምረው እርስዎ ራስዎ ለመሆን የበለጠ ጊዜ ሲኖርዎት ነው።"
    },
    {
        "id": "about-page-greeting-title-2",
        "am": "ጥሩ ይሰማዎት።"
    },
    {
        "id": "about-page-greeting-title-3",
        "am": "አካል እና አእምሮ።"
    },
    {
        "id": "about-page-greeting-description-4",
        "am": "ለመላ አካልና አእምሮ ደህንነት ከመቶዎች የሚቆጠሩ የአካል ብቃት እንቅስቃሴዎችን፣ ጤናማ የምግብ ዝግጅቶችን፣ አረፋጅ ማሰላሰያዎችን እና የባለሙያ ጽሑፎችን ይምረጡ።"
    }
]